<?xml version="1.0" encoding="utf-8"?>
<TextureAtlas imagePath="pinkeline alt.png">
	<!-- Created with Adobe Animate version 21.0.2.37893 -->
	<!-- http://www.adobe.com/products/animate.html -->
	<SubTexture name="madi down b0000" x="10" y="10" width="699" height="611"/>
	<SubTexture name="madi down b0001" x="10" y="10" width="699" height="611"/>
	<SubTexture name="madi down b0002" x="719" y="10" width="699" height="611"/>
	<SubTexture name="madi down b0003" x="719" y="10" width="699" height="611"/>
	<SubTexture name="madi down b0004" x="1428" y="10" width="699" height="611"/>
	<SubTexture name="madi down b0005" x="1428" y="10" width="699" height="611"/>
	<SubTexture name="madi down b0006" x="1428" y="10" width="699" height="611"/>
	<SubTexture name="madi down b0007" x="1428" y="10" width="699" height="611"/>
	<SubTexture name="madi down b0008" x="1428" y="10" width="699" height="611"/>
	<SubTexture name="madi down b0009" x="1428" y="10" width="699" height="611"/>
	<SubTexture name="madi down b0010" x="1428" y="10" width="699" height="611"/>
	<SubTexture name="madi down b0011" x="1428" y="10" width="699" height="611"/>
	<SubTexture name="madi down b0012" x="1428" y="10" width="699" height="611"/>
	<SubTexture name="madi down b0013" x="1428" y="10" width="699" height="611"/>
	<SubTexture name="madi down b0014" x="1428" y="10" width="699" height="611"/>
	<SubTexture name="madi down b0015" x="1428" y="10" width="699" height="611"/>
	<SubTexture name="madi idle b0000" x="2137" y="10" width="675" height="805"/>
	<SubTexture name="madi idle b0001" x="2137" y="10" width="675" height="805"/>
	<SubTexture name="madi idle b0002" x="2822" y="10" width="675" height="805"/>
	<SubTexture name="madi idle b0003" x="2822" y="10" width="675" height="805"/>
	<SubTexture name="madi idle b0004" x="10" y="825" width="675" height="805"/>
	<SubTexture name="madi idle b0005" x="10" y="825" width="675" height="805"/>
	<SubTexture name="madi idle b0006" x="695" y="825" width="675" height="805"/>
	<SubTexture name="madi idle b0007" x="1380" y="825" width="675" height="805"/>
	<SubTexture name="madi idle b0008" x="1380" y="825" width="675" height="805"/>
	<SubTexture name="madi idle b0009" x="2065" y="825" width="675" height="805"/>
	<SubTexture name="madi idle b0010" x="2065" y="825" width="675" height="805"/>
	<SubTexture name="madi idle b0011" x="2065" y="825" width="675" height="805"/>
	<SubTexture name="madi idle b0012" x="2065" y="825" width="675" height="805"/>
	<SubTexture name="madi idle b0013" x="2065" y="825" width="675" height="805"/>
	<SubTexture name="madi idle b0014" x="2065" y="825" width="675" height="805"/>
	<SubTexture name="madi idle b0015" x="2065" y="825" width="675" height="805"/>
	<SubTexture name="madi left b0000" x="2750" y="825" width="748" height="799"/>
	<SubTexture name="madi left b0001" x="2750" y="825" width="748" height="799"/>
	<SubTexture name="madi left b0002" x="10" y="1640" width="748" height="799"/>
	<SubTexture name="madi left b0003" x="10" y="1640" width="748" height="799"/>
	<SubTexture name="madi left b0004" x="768" y="1640" width="748" height="799"/>
	<SubTexture name="madi left b0005" x="768" y="1640" width="748" height="799"/>
	<SubTexture name="madi left b0006" x="768" y="1640" width="748" height="799"/>
	<SubTexture name="madi left b0007" x="768" y="1640" width="748" height="799"/>
	<SubTexture name="madi left b0008" x="768" y="1640" width="748" height="799"/>
	<SubTexture name="madi left b0009" x="768" y="1640" width="748" height="799"/>
	<SubTexture name="madi left b0010" x="768" y="1640" width="748" height="799"/>
	<SubTexture name="madi left b0011" x="768" y="1640" width="748" height="799"/>
	<SubTexture name="madi left b0012" x="768" y="1640" width="748" height="799"/>
	<SubTexture name="madi left b0013" x="768" y="1640" width="748" height="799"/>
	<SubTexture name="madi left b0014" x="768" y="1640" width="748" height="799"/>
	<SubTexture name="madi right b0000" x="1526" y="1640" width="779" height="709"/>
	<SubTexture name="madi right b0001" x="1526" y="1640" width="779" height="709"/>
	<SubTexture name="madi right b0002" x="2315" y="1640" width="779" height="709"/>
	<SubTexture name="madi right b0003" x="2315" y="1640" width="779" height="709"/>
	<SubTexture name="madi right b0004" x="3104" y="1640" width="779" height="709"/>
	<SubTexture name="madi right b0005" x="3104" y="1640" width="779" height="709"/>
	<SubTexture name="madi right b0006" x="3104" y="1640" width="779" height="709"/>
	<SubTexture name="madi right b0007" x="3104" y="1640" width="779" height="709"/>
	<SubTexture name="madi right b0008" x="3104" y="1640" width="779" height="709"/>
	<SubTexture name="madi right b0009" x="3104" y="1640" width="779" height="709"/>
	<SubTexture name="madi right b0010" x="3104" y="1640" width="779" height="709"/>
	<SubTexture name="madi right b0011" x="3104" y="1640" width="779" height="709"/>
	<SubTexture name="madi right b0012" x="3104" y="1640" width="779" height="709"/>
	<SubTexture name="madi right b0013" x="3104" y="1640" width="779" height="709"/>
	<SubTexture name="madi right b0014" x="3104" y="1640" width="779" height="709"/>
	<SubTexture name="madi up b0000" x="10" y="2449" width="649" height="993"/>
	<SubTexture name="madi up b0001" x="10" y="2449" width="649" height="993"/>
	<SubTexture name="madi up b0002" x="669" y="2449" width="649" height="993"/>
	<SubTexture name="madi up b0003" x="669" y="2449" width="649" height="993"/>
	<SubTexture name="madi up b0004" x="1328" y="2449" width="649" height="993"/>
	<SubTexture name="madi up b0005" x="1328" y="2449" width="649" height="993"/>
	<SubTexture name="madi up b0006" x="1328" y="2449" width="649" height="993"/>
	<SubTexture name="madi up b0007" x="1328" y="2449" width="649" height="993"/>
	<SubTexture name="madi up b0008" x="1328" y="2449" width="649" height="993"/>
	<SubTexture name="madi up b0009" x="1328" y="2449" width="649" height="993"/>
	<SubTexture name="madi up b0010" x="1328" y="2449" width="649" height="993"/>
	<SubTexture name="madi up b0011" x="1328" y="2449" width="649" height="993"/>
	<SubTexture name="madi up b0012" x="1328" y="2449" width="649" height="993"/>
	<SubTexture name="madi up b0013" x="1328" y="2449" width="649" height="993"/>
	<SubTexture name="madi up b0014" x="1328" y="2449" width="649" height="993"/>
</TextureAtlas>
